stonehenge/__init__.py
stonehenge/admin/__init__.py
stonehenge/admin/handlers.py
stonehenge/admin/router.py
stonehenge/application.py
stonehenge/auth/__init__.py
stonehenge/auth/models.py
stonehenge/cms/__init__.py
stonehenge/cms/handlers.py
stonehenge/cms/router.py
stonehenge/commands.py
stonehenge/components/__init__.py
stonehenge/components/component.py
stonehenge/components/html/__init__.py
stonehenge/components/html/styles.py
stonehenge/components/ui/__init__.py
stonehenge/components/ui/base.py
stonehenge/components/ui/box.py
stonehenge/components/ui/constants.py
stonehenge/components/ui/container.py
stonehenge/components/ui/header.py
stonehenge/components/ui/link.py
stonehenge/db/__init__.py
stonehenge/db/columns.py
stonehenge/db/commands.py
stonehenge/db/databases.py
stonehenge/db/defaults.py
stonehenge/db/exceptions.py
stonehenge/db/fields.py
stonehenge/db/migrations/__init__.py
stonehenge/db/migrations/exceptions.py
stonehenge/db/migrations/migration.py
stonehenge/db/migrations/types.py
stonehenge/db/migrations/utils.py
stonehenge/db/models.py
stonehenge/db/operations.py
stonehenge/db/queries.py
stonehenge/db/utils.py
stonehenge/exceptions.py
stonehenge/handlers/__init__.py
stonehenge/handlers/contrib.py
stonehenge/middlewares/__init__.py
stonehenge/middlewares/types.py
stonehenge/migrations/__init__.py
stonehenge/modules/__init__.py
stonehenge/modules/defaults.py
stonehenge/requests/__init__.py
stonehenge/requests/methods.py
stonehenge/requests/request.py
stonehenge/requests/utils.py
stonehenge/responses/__init__.py
stonehenge/responses/content_types.py
stonehenge/responses/response.py
stonehenge/routers/__init__.py
stonehenge/routers/defaults.py
stonehenge/routers/dynamic_routes.py
stonehenge/routers/route.py
stonehenge/routers/route_map.py
stonehenge/routers/router.py
stonehenge/routers/utils.py
stonehenge/server/__init__.py
stonehenge/server/commands.py
stonehenge/status.py
stonehenge-0.1.0.dist-info/LICENSE
stonehenge-0.1.0.dist-info/WHEEL
stonehenge-0.1.0.dist-info/METADATA
stonehenge-0.1.0.dist-info/RECORD
